unity_raw_to_exr.py
unity_raw_to_exr-0.0.2.dist-info/LICENSE.TXT
unity_raw_to_exr-0.0.2.dist-info/METADATA
unity_raw_to_exr-0.0.2.dist-info/WHEEL
unity_raw_to_exr-0.0.2.dist-info/top_level.txt
unity_raw_to_exr-0.0.2.dist-info/RECORD
