Metadata-Version: 2.1
Name: unity-raw-to-exr
Version: 0.0.2
Summary: A utility for converting Unity Terrain Heightmap data from 16-bit raw to 16-bit exr
Home-page: https://github.com/TonyMarkham
Author: Tony Markham
Author-email: myonlineentity@gmail.com
License: UNKNOWN
Platform: UNKNOWN
Classifier: Programming Language :: Python :: 3
Classifier: Programming Language :: Python :: 3.7
Classifier: License :: OSI Approved :: GNU General Public License v3 (GPLv3)
Classifier: Operating System :: OS Independent
Requires-Dist: numpy
Requires-Dist: imageio
Provides-Extra: dev
Requires-Dist: pytest (>=3.7) ; extra == 'dev'
Requires-Dist: check-manifest ; extra == 'dev'
